version_pioneer/__init__.py
version_pioneer/api.py
version_pioneer/template.py
version_pioneer/versionscript.py
version_pioneer/build/__init__.py
version_pioneer/build/hatchling/__init__.py
version_pioneer/build/hatchling/build_hook.py
version_pioneer/build/hatchling/hooks.py
version_pioneer/build/hatchling/version_source.py
version_pioneer/build/pdm/__init__.py
version_pioneer/build/pdm/hooks.py
version_pioneer/build/setuptools/__init__.py
version_pioneer/build/setuptools/cmdclass.py
version_pioneer/build/setuptools/get_version.py
version_pioneer/cli/__init__.py
version_pioneer/cli/docstring.py
version_pioneer/cli/main.py
version_pioneer/utils/__init__.py
version_pioneer/utils/build.py
version_pioneer/utils/diff.py
version_pioneer/utils/files.py
version_pioneer/utils/toml.py
version_pioneer/utils/versionscript.py
version_pioneer/_version.py
version_pioneer-0.0.15.dist-info/METADATA
version_pioneer-0.0.15.dist-info/WHEEL
version_pioneer-0.0.15.dist-info/entry_points.txt
version_pioneer-0.0.15.dist-info/licenses/LICENSE
version_pioneer-0.0.15.dist-info/RECORD
