Metadata-Version: 2.4
Name: version-pioneer
Version: 0.0.15
Summary: VCS-based project version management for any build backend (setuptools, hatchling, pdm) extensible to any programming language.
Project-URL: Homepage, https://github.com/kiyoon/version-pioneer
Author: Kiyoon Kim
License: MIT License
License-File: LICENSE
Keywords: git,project,project-management,vcs,version,version-control,version-number,version-scheme,version-strategy,version-string,versioning,versioning-scheme,versioning-strategy
Classifier: License :: OSI Approved :: MIT License
Classifier: Programming Language :: Python
Classifier: Programming Language :: Python :: 3
Classifier: Programming Language :: Python :: 3.8
Classifier: Programming Language :: Python :: 3.9
Classifier: Programming Language :: Python :: 3.10
Classifier: Programming Language :: Python :: 3.11
Classifier: Programming Language :: Python :: 3.12
Classifier: Programming Language :: Python :: 3.13
Classifier: Programming Language :: Python :: 3.14
Classifier: Programming Language :: Python :: Implementation :: CPython
Classifier: Programming Language :: Python :: Implementation :: PyPy
Requires-Python: <4,>=3.8
Requires-Dist: tomli>=2.0.0; python_version < '3.11'
Provides-Extra: cli
Requires-Dist: docstring-parser; extra == 'cli'
Requires-Dist: typer>=0.12.4; extra == 'cli'
Requires-Dist: typing-extensions; (python_version < '3.9') and extra == 'cli'
Requires-Dist: verboselogs; extra == 'cli'
Requires-Dist: wheel; extra == 'cli'
